{
  "id": "F35434",
  "children": [
    {
      "type": "element",
      "name": "Publication",
      "attributes": {
        "xmlns:dc": "http://purl.org/dc/elements/1.1/",
        "xmlns:xsi": "http://www.w3.org/2001/XMLSchema-instance",
        "ID": "F35434",
        "type": "Fiche Question-réponse conditionnée",
        "xsi:noNamespaceSchemaLocation": "../Schemas/3.4/Publication.xsd",
        "spUrl": "https://www.service-public.gouv.fr/particuliers/vosdroits/F35434"
      },
      "children": [
        {
          "type": "element",
          "name": "dc:title",
          "children": [
            {
              "type": "text",
              "text": "CSE : quand l'employeur doit-il organiser des élections partielles ?"
            }
          ]
        },
        {
          "type": "element",
          "name": "dc:creator",
          "children": [
            {
              "type": "text",
              "text": "Direction de l'information légale et administrative"
            }
          ]
        },
        {
          "type": "element",
          "name": "dc:subject",
          "children": [
            {
              "type": "text",
              "text": "Travail - Formation"
            }
          ]
        },
        {
          "type": "element",
          "name": "dc:description",
          "children": [
            {
              "type": "text",
              "text": "L’employeur peut être amené à organiser des élections partielles lorsque des membres du CSE démissionnent en cours de mandat."
            }
          ]
        },
        {
          "type": "element",
          "name": "dc:publisher",
          "children": [
            {
              "type": "text",
              "text": "Direction de l'information légale et administrative"
            }
          ]
        },
        {
          "type": "element",
          "name": "dc:contributor",
          "children": [
            {
              "type": "text",
              "text": "Service Public / Direction de l'information légale et administrative (Premier ministre)"
            }
          ]
        },
        {
          "type": "element",
          "name": "dc:date",
          "children": [
            {
              "type": "text",
              "text": "modified 2025-08-11"
            }
          ]
        },
        {
          "type": "element",
          "name": "dc:type",
          "children": [
            {
              "type": "text",
              "text": "Question-réponse"
            }
          ]
        },
        {
          "type": "element",
          "name": "dc:format",
          "children": [
            {
              "type": "text",
              "text": "text/xml"
            }
          ]
        },
        {
          "type": "element",
          "name": "dc:identifier",
          "children": [
            {
              "type": "text",
              "text": "F35434"
            }
          ]
        },
        {
          "type": "element",
          "name": "dc:source",
          "children": [
            {
              "type": "text",
              "text": "https://www.legifrance.gouv.fr/codes/article_lc/LEGIARTI000035651133/"
            }
          ]
        },
        {
          "type": "element",
          "name": "dc:language",
          "children": [
            {
              "type": "text",
              "text": "Fr"
            }
          ]
        },
        {
          "type": "element",
          "name": "dc:relation",
          "children": [
            {
              "type": "text",
              "text": "isPartOf N518"
            }
          ]
        },
        {
          "type": "element",
          "name": "dc:coverage",
          "children": [
            {
              "type": "text",
              "text": "France entière"
            }
          ]
        },
        {
          "type": "element",
          "name": "dc:rights",
          "children": [
            {
              "type": "text",
              "text": "https://www.service-public.gouv.fr/a-propos/mentions-legales"
            }
          ]
        },
        {
          "type": "element",
          "name": "SurTitre",
          "children": [
            {
              "type": "text",
              "text": "Question-réponse"
            }
          ]
        },
        {
          "type": "element",
          "name": "Audience",
          "children": [
            {
              "type": "text",
              "text": "Particuliers"
            }
          ]
        },
        {
          "type": "element",
          "name": "Canal",
          "children": [
            {
              "type": "text",
              "text": "www.service-public.fr"
            }
          ]
        },
        {
          "type": "element",
          "name": "FilDAriane",
          "children": [
            {
              "type": "element",
              "name": "Niveau",
              "attributes": {
                "ID": "Particuliers"
              },
              "children": [
                {
                  "type": "text",
                  "text": "Accueil particuliers"
                }
              ]
            },
            {
              "type": "element",
              "name": "Niveau",
              "attributes": {
                "ID": "N19806"
              },
              "children": [
                {
                  "type": "text",
                  "text": "Travail - Formation"
                }
              ]
            },
            {
              "type": "element",
              "name": "Niveau",
              "attributes": {
                "ID": "N518"
              },
              "children": [
                {
                  "type": "text",
                  "text": "Représentation du personnel dans l'entreprise"
                }
              ]
            },
            {
              "type": "element",
              "name": "Niveau",
              "attributes": {
                "ID": "F35434",
                "type": "Fiche Question-réponse conditionnée"
              },
              "children": [
                {
                  "type": "text",
                  "text": "CSE : quand l'employeur doit-il organiser des élections partielles ?"
                }
              ]
            }
          ]
        },
        {
          "type": "element",
          "name": "Theme",
          "attributes": {
            "ID": "N19806"
          },
          "children": [
            {
              "type": "element",
              "name": "Titre",
              "children": [
                {
                  "type": "text",
                  "text": "Travail - Formation"
                }
              ]
            }
          ]
        },
        {
          "type": "element",
          "name": "SousThemePere",
          "attributes": {
            "ID": "N19966"
          },
          "children": [
            {
              "type": "text",
              "text": "Relations individuelles et collectives de travail"
            }
          ]
        },
        {
          "type": "element",
          "name": "DossierPere",
          "attributes": {
            "ID": "N518"
          },
          "children": [
            {
              "type": "element",
              "name": "Titre",
              "children": [
                {
                  "type": "text",
                  "text": "Représentation du personnel dans l'entreprise"
                }
              ]
            },
            {
              "type": "element",
              "name": "Fiche",
              "attributes": {
                "ID": "F34474"
              },
              "children": [
                {
                  "type": "text",
                  "text": "Comité social et économique (CSE)"
                }
              ]
            },
            {
              "type": "element",
              "name": "Fiche",
              "attributes": {
                "ID": "F102"
              },
              "children": [
                {
                  "type": "text",
                  "text": "Délégué syndical"
                }
              ]
            },
            {
              "type": "element",
              "name": "Fiche",
              "attributes": {
                "ID": "F32078"
              },
              "children": [
                {
                  "type": "text",
                  "text": "Représentant de la section syndicale (RSS)"
                }
              ]
            }
          ]
        },
        {
          "type": "element",
          "name": "Introduction",
          "children": [
            {
              "type": "element",
              "name": "Texte",
              "children": [
                {
                  "type": "element",
                  "name": "Paragraphe",
                  "children": [
                    {
                      "type": "text",
                      "text": "L'employeur a l'obligation de mettre en place un comité social et économique (CSE) dans les entreprises de 11 salariés et plus. Lorsqu'un ou plusieurs membres du CSE démissionnent en cours de mandat, ils sont remplacés par des suppléants. Lorsqu'il n'y a pas ou plus de suppléants, l'employeur peut être amené à organiser des élections partielles. Nous faisons le point sur la réglementation."
                    }
                  ]
                }
              ]
            }
          ]
        },
        {
          "type": "element",
          "name": "Texte",
          "children": [
            {
              "type": "element",
              "name": "Paragraphe",
              "children": [
                {
                  "type": "text",
                  "text": "L'employeur doit organiser des élections partielles si un "
                },
                {
                  "type": "element",
                  "name": "LienIntra",
                  "attributes": {
                    "LienID": "R57503",
                    "type": "Définition de glossaire"
                  },
                  "children": [
                    {
                      "type": "text",
                      "text": "collège électoral"
                    }
                  ]
                },
                {
                  "type": "text",
                  "text": " n'est plus représenté ou si le nombre des membres "
                },
                {
                  "type": "element",
                  "name": "MiseEnEvidence",
                  "children": [
                    {
                      "type": "text",
                      "text": "titulaires"
                    }
                  ]
                },
                {
                  "type": "text",
                  "text": " a été réduit de moitié ou plus."
                }
              ]
            },
            {
              "type": "element",
              "name": "Paragraphe",
              "children": [
                {
                  "type": "text",
                  "text": "L'obligation d'organiser des élections partielles dépend du moment où se produit l'évènement par rapport à la date prévue de fin du mandat :"
                }
              ]
            },
            {
              "type": "element",
              "name": "BlocCas",
              "attributes": {
                "affichage": "radio"
              },
              "children": [
                {
                  "type": "element",
                  "name": "Cas",
                  "children": [
                    {
                      "type": "element",
                      "name": "Titre",
                      "children": [
                        {
                          "type": "text",
                          "text": "Mandat se terminant dans 6 mois ou plus"
                        }
                      ]
                    },
                    {
                      "type": "element",
                      "name": "Introduction",
                      "children": [
                        {
                          "type": "element",
                          "name": "Paragraphe",
                          "children": [
                            {
                              "type": "text",
                              "text": "L'employeur a l'obligation d'organiser des élections partielles si un collège électoral a cessé d'être représenté ou si le CSE a perdu la moitié de ses membres titulaires ou plus."
                            }
                          ]
                        }
                      ]
                    },
                    {
                      "type": "element",
                      "name": "BlocCas",
                      "attributes": {
                        "affichage": "radio"
                      },
                      "children": [
                        {
                          "type": "element",
                          "name": "Cas",
                          "children": [
                            {
                              "type": "element",
                              "name": "Titre",
                              "children": [
                                {
                                  "type": "text",
                                  "text": "Un collège électoral a cessé d'être représenté"
                                }
                              ]
                            },
                            {
                              "type": "element",
                              "name": "Paragraphe",
                              "children": [
                                {
                                  "type": "text",
                                  "text": "Lorsqu'un collège n'est plus représenté, l'employeur doit organiser des élections partielles. Les membres doivent avoir "
                                },
                                {
                                  "type": "element",
                                  "name": "MiseEnEvidence",
                                  "children": [
                                    {
                                      "type": "text",
                                      "text": "cessé définitivement"
                                    }
                                  ]
                                },
                                {
                                  "type": "text",
                                  "text": " leur mandat ou avoir quitté l'entreprise (par exemple, démission de la fonction de représentant du personnel, démission ou licenciement du salarié). Et il n'y a plus de suppléants pouvant remplacer les titulaires."
                                }
                              ]
                            },
                            {
                              "type": "element",
                              "name": "Paragraphe",
                              "children": [
                                {
                                  "type": "text",
                                  "text": "Seul ce collège est concerné par les élections. Elles sont organisées pour les titulaires et pour les suppléants."
                                }
                              ]
                            },
                            {
                              "type": "element",
                              "name": "Paragraphe",
                              "children": [
                                {
                                  "type": "text",
                                  "text": "Les élections partielles s'organisent et se déroulent selon les mêmes règles que les "
                                },
                                {
                                  "type": "element",
                                  "name": "LienInterne",
                                  "attributes": {
                                    "LienPublication": "F23513",
                                    "type": "Fiche d'information conditionnée",
                                    "audience": "Professionnels"
                                  },
                                  "children": [
                                    {
                                      "type": "text",
                                      "text": "élections ordinaires"
                                    }
                                  ]
                                },
                                {
                                  "type": "text",
                                  "text": "."
                                }
                              ]
                            },
                            {
                              "type": "element",
                              "name": "Paragraphe",
                              "children": [
                                {
                                  "type": "text",
                                  "text": "L'élection se déroule dans les conditions fixées par le protocole d'accord préélectoral (PAP) conclu lors de l'élection initiale."
                                }
                              ]
                            },
                            {
                              "type": "element",
                              "name": "Paragraphe",
                              "children": [
                                {
                                  "type": "text",
                                  "text": "Les candidats sont élus pour "
                                },
                                {
                                  "type": "element",
                                  "name": "MiseEnEvidence",
                                  "children": [
                                    {
                                      "type": "text",
                                      "text": "la durée du mandat restant à courir"
                                    }
                                  ]
                                },
                                {
                                  "type": "text",
                                  "text": "."
                                }
                              ]
                            },
                            {
                              "type": "element",
                              "name": "Paragraphe",
                              "children": [
                                {
                                  "type": "text",
                                  "text": "L'employeur doit mettre à jour la liste électorale pour prendre en compte les changements suivants ;"
                                }
                              ]
                            },
                            {
                              "type": "element",
                              "name": "Liste",
                              "attributes": {
                                "type": "puce"
                              },
                              "children": [
                                {
                                  "type": "element",
                                  "name": "Item",
                                  "children": [
                                    {
                                      "type": "element",
                                      "name": "Paragraphe",
                                      "children": [
                                        {
                                          "type": "text",
                                          "text": "Nouveaux salariés"
                                        }
                                      ]
                                    }
                                  ]
                                },
                                {
                                  "type": "element",
                                  "name": "Item",
                                  "children": [
                                    {
                                      "type": "element",
                                      "name": "Paragraphe",
                                      "children": [
                                        {
                                          "type": "text",
                                          "text": "Salariés qui ne remplissaient pas les conditions pour être électeurs lors de la précédente élection"
                                        }
                                      ]
                                    }
                                  ]
                                },
                                {
                                  "type": "element",
                                  "name": "Item",
                                  "children": [
                                    {
                                      "type": "element",
                                      "name": "Paragraphe",
                                      "children": [
                                        {
                                          "type": "text",
                                          "text": "Salariés qui ont quitté l'entreprise"
                                        }
                                      ]
                                    }
                                  ]
                                },
                                {
                                  "type": "element",
                                  "name": "Item",
                                  "children": [
                                    {
                                      "type": "element",
                                      "name": "Paragraphe",
                                      "children": [
                                        {
                                          "type": "text",
                                          "text": "Changements de qualification des salariés. Par exemple, un salarié devenu cadre à la suite d'une promotion doit voter pour le collège des cadres, même s'il avait voté pour le collège des techniciens et agents de maîtrise lors de l'élection initiale."
                                        }
                                      ]
                                    }
                                  ]
                                }
                              ]
                            }
                          ]
                        },
                        {
                          "type": "element",
                          "name": "Cas",
                          "children": [
                            {
                              "type": "element",
                              "name": "Titre",
                              "children": [
                                {
                                  "type": "text",
                                  "text": "Le CSE a perdu la moitié de ses membres titulaires ou plus"
                                }
                              ]
                            },
                            {
                              "type": "element",
                              "name": "Paragraphe",
                              "children": [
                                {
                                  "type": "text",
                                  "text": "Lorsque le CSE a perdu la moitié de ses membres "
                                },
                                {
                                  "type": "element",
                                  "name": "MiseEnEvidence",
                                  "children": [
                                    {
                                      "type": "text",
                                      "text": "titulaires"
                                    }
                                  ]
                                },
                                {
                                  "type": "text",
                                  "text": " ou plus, l'employeur doit organiser des élections partielles. Les membres doivent avoir "
                                },
                                {
                                  "type": "element",
                                  "name": "MiseEnEvidence",
                                  "children": [
                                    {
                                      "type": "text",
                                      "text": "cessé définitivement"
                                    }
                                  ]
                                },
                                {
                                  "type": "text",
                                  "text": " leur mandat ou avoir quitté l'entreprise (par exemple, démission de la fonction de représentant du personnel, démission ou licenciement du salarié). Et il n'y a plus de suppléants pouvant remplacer les titulaires."
                                }
                              ]
                            },
                            {
                              "type": "element",
                              "name": "Paragraphe",
                              "children": [
                                {
                                  "type": "text",
                                  "text": "Tous les sièges vacants de tous les collèges sont concernés par cette élection. Des listes distinctes sont établies pour les titulaires et les suppléants."
                                }
                              ]
                            },
                            {
                              "type": "element",
                              "name": "Paragraphe",
                              "children": [
                                {
                                  "type": "text",
                                  "text": "Les élections partielles s'organisent et se déroulent selon les mêmes règles que les "
                                },
                                {
                                  "type": "element",
                                  "name": "LienInterne",
                                  "attributes": {
                                    "LienPublication": "F23513",
                                    "type": "Fiche d'information conditionnée",
                                    "audience": "Professionnels"
                                  },
                                  "children": [
                                    {
                                      "type": "text",
                                      "text": "élections ordinaires"
                                    }
                                  ]
                                },
                                {
                                  "type": "text",
                                  "text": "."
                                }
                              ]
                            },
                            {
                              "type": "element",
                              "name": "Paragraphe",
                              "children": [
                                {
                                  "type": "text",
                                  "text": "L'élection se déroule dans les conditions fixées par le protocole d'accord préélectoral (PAP) conclu lors de l'élection initiale."
                                }
                              ]
                            },
                            {
                              "type": "element",
                              "name": "Paragraphe",
                              "children": [
                                {
                                  "type": "text",
                                  "text": "Les candidats sont élus pour "
                                },
                                {
                                  "type": "element",
                                  "name": "MiseEnEvidence",
                                  "children": [
                                    {
                                      "type": "text",
                                      "text": "la durée du mandat restant à courir"
                                    }
                                  ]
                                },
                                {
                                  "type": "text",
                                  "text": "."
                                }
                              ]
                            },
                            {
                              "type": "element",
                              "name": "Paragraphe",
                              "children": [
                                {
                                  "type": "text",
                                  "text": "L'employeur doit mettre à jour la liste électorale pour prendre en compte les changements suivants ;"
                                }
                              ]
                            },
                            {
                              "type": "element",
                              "name": "Liste",
                              "attributes": {
                                "type": "puce"
                              },
                              "children": [
                                {
                                  "type": "element",
                                  "name": "Item",
                                  "children": [
                                    {
                                      "type": "element",
                                      "name": "Paragraphe",
                                      "children": [
                                        {
                                          "type": "text",
                                          "text": "Nouveaux salariés"
                                        }
                                      ]
                                    }
                                  ]
                                },
                                {
                                  "type": "element",
                                  "name": "Item",
                                  "children": [
                                    {
                                      "type": "element",
                                      "name": "Paragraphe",
                                      "children": [
                                        {
                                          "type": "text",
                                          "text": "Salariés qui ne remplissaient pas les conditions pour être électeurs lors de la précédente élection"
                                        }
                                      ]
                                    }
                                  ]
                                },
                                {
                                  "type": "element",
                                  "name": "Item",
                                  "children": [
                                    {
                                      "type": "element",
                                      "name": "Paragraphe",
                                      "children": [
                                        {
                                          "type": "text",
                                          "text": "Salariés qui ont quitté l'entreprise"
                                        }
                                      ]
                                    }
                                  ]
                                },
                                {
                                  "type": "element",
                                  "name": "Item",
                                  "children": [
                                    {
                                      "type": "element",
                                      "name": "Paragraphe",
                                      "children": [
                                        {
                                          "type": "text",
                                          "text": "Changements de qualification des salariés. Par exemple, un salarié devenu cadre à la suite d'une promotion doit voter pour le collège des cadres, même s'il avait voté pour le collège des techniciens et agents de maîtrise lors de l'élection initiale."
                                        }
                                      ]
                                    }
                                  ]
                                }
                              ]
                            }
                          ]
                        }
                      ]
                    }
                  ]
                },
                {
                  "type": "element",
                  "name": "Cas",
                  "children": [
                    {
                      "type": "element",
                      "name": "Titre",
                      "children": [
                        {
                          "type": "text",
                          "text": "Mandat se terminant dans moins de 6 mois"
                        }
                      ]
                    },
                    {
                      "type": "element",
                      "name": "Paragraphe",
                      "children": [
                        {
                          "type": "text",
                          "text": "L'employeur n'a pas l'obligation d'organiser des élections partielles lorsque ces événements se produisent dans les 6 mois précédant le terme du mandat."
                        }
                      ]
                    },
                    {
                      "type": "element",
                      "name": "Paragraphe",
                      "children": [
                        {
                          "type": "text",
                          "text": "Le CSE fonctionnera à effectif réduit jusqu'à la fin du mandat."
                        }
                      ]
                    }
                  ]
                }
              ]
            }
          ]
        },
        {
          "type": "element",
          "name": "VoirAussi",
          "attributes": {
            "important": "non"
          },
          "children": [
            {
              "type": "element",
              "name": "Fiche",
              "attributes": {
                "ID": "F23513",
                "audience": "Professionnels"
              },
              "children": [
                {
                  "type": "element",
                  "name": "Titre",
                  "children": [
                    {
                      "type": "text",
                      "text": "Élections du CSE dans les entreprises de 11 salariés et plus"
                    }
                  ]
                },
                {
                  "type": "element",
                  "name": "Theme",
                  "attributes": {
                    "ID": "N24267"
                  },
                  "children": [
                    {
                      "type": "element",
                      "name": "Titre",
                      "children": [
                        {
                          "type": "text",
                          "text": "Ressources humaines"
                        }
                      ]
                    }
                  ]
                }
              ]
            }
          ]
        },
        {
          "type": "element",
          "name": "Reference",
          "attributes": {
            "type": "Texte de référence",
            "URL": "https://www.legifrance.gouv.fr/codes/article_lc/LEGIARTI000035651133/",
            "ID": "R49876"
          },
          "children": [
            {
              "type": "element",
              "name": "Titre",
              "children": [
                {
                  "type": "text",
                  "text": "Code du travail : article L2314-10"
                }
              ]
            },
            {
              "type": "element",
              "name": "Complement",
              "children": [
                {
                  "type": "text",
                  "text": "Organisation des élections partielles"
                }
              ]
            }
          ]
        },
        {
          "type": "element",
          "name": "PourEnSavoirPlus",
          "attributes": {
            "type": "Information pratique",
            "ID": "R43498",
            "URL": "https://www.elections-professionnelles.travail.gouv.fr/",
            "audience": "Particuliers"
          },
          "children": [
            {
              "type": "element",
              "name": "Titre",
              "children": [
                {
                  "type": "text",
                  "text": "Site dédié aux élections professionnelles"
                }
              ]
            },
            {
              "type": "element",
              "name": "Source",
              "attributes": {
                "ID": "R30661"
              },
              "children": [
                {
                  "type": "text",
                  "text": "Ministère chargé du travail"
                }
              ]
            }
          ]
        },
        {
          "type": "element",
          "name": "PourEnSavoirPlus",
          "attributes": {
            "type": "Information pratique",
            "ID": "R50624",
            "URL": "https://travail-emploi.gouv.fr/dialogue-social/comite-social-et-economique-cse",
            "audience": "Particuliers"
          },
          "children": [
            {
              "type": "element",
              "name": "Titre",
              "children": [
                {
                  "type": "text",
                  "text": "Comité social et économique : dossier"
                }
              ]
            },
            {
              "type": "element",
              "name": "Source",
              "attributes": {
                "ID": "R30661"
              },
              "children": [
                {
                  "type": "text",
                  "text": "Ministère chargé du travail"
                }
              ]
            }
          ]
        },
        {
          "type": "element",
          "name": "Definition",
          "attributes": {
            "ID": "R57503"
          },
          "children": [
            {
              "type": "element",
              "name": "Titre",
              "children": [
                {
                  "type": "text",
                  "text": "Collège électoral CSE"
                }
              ]
            },
            {
              "type": "element",
              "name": "Texte",
              "children": [
                {
                  "type": "element",
                  "name": "Paragraphe",
                  "children": [
                    {
                      "type": "text",
                      "text": "Groupe de salariés qui votent pour élire leurs propres représentants du personnel au CSE. Plusieurs catégories de personnel composent les différents collèges : ouvriers, employés et agents de maîtrise, techniciens et cadres."
                    }
                  ]
                }
              ]
            }
          ]
        }
      ]
    }
  ]
}