{
  "id": "N20398",
  "children": [
    {
      "type": "element",
      "name": "Publication",
      "attributes": {
        "xmlns:dc": "http://purl.org/dc/elements/1.1/",
        "xmlns:xsi": "http://www.w3.org/2001/XMLSchema-instance",
        "ID": "N20398",
        "type": "Dossier",
        "xsi:noNamespaceSchemaLocation": "../Schemas/3.4/Publication.xsd",
        "spUrl": "https://www.service-public.gouv.fr/particuliers/vosdroits/N20398"
      },
      "children": [
        {
          "type": "element",
          "name": "dc:title",
          "children": [
            {
              "type": "text",
              "text": "Bourses et aides pour étudiant"
            }
          ]
        },
        {
          "type": "element",
          "name": "dc:creator",
          "children": [
            {
              "type": "text",
              "text": "Direction de l'information légale et administrative"
            }
          ]
        },
        {
          "type": "element",
          "name": "dc:subject",
          "children": [
            {
              "type": "text",
              "text": "Famille - Scolarité"
            }
          ]
        },
        {
          "type": "element",
          "name": "dc:description",
          "children": [
            {
              "type": "text",
              "text": "Si vous êtes étudiant ou que vous entrez en première année d'études supérieures, vous pouvez prétendre à des bourses et à des aides en fonction de votre situation. Si vous rencontrez des difficultés financières pour entreprendre et poursuivre vos études, vous pouvez également bénéficier d'aides spécifiques. Des aides à la mobilité, à l'insertion professionnelle et à l’accès à la fonction publique peuvent également vous être attribuées."
            }
          ]
        },
        {
          "type": "element",
          "name": "dc:publisher",
          "children": [
            {
              "type": "text",
              "text": "Direction de l'information légale et administrative"
            }
          ]
        },
        {
          "type": "element",
          "name": "dc:contributor",
          "children": [
            {
              "type": "text",
              "text": "Service Public / Direction de l'information légale et administrative (Premier ministre)"
            }
          ]
        },
        {
          "type": "element",
          "name": "dc:date",
          "children": [
            {
              "type": "text",
              "text": "modified 2023-10-16"
            }
          ]
        },
        {
          "type": "element",
          "name": "dc:type",
          "children": [
            {
              "type": "text",
              "text": "Dossier"
            }
          ]
        },
        {
          "type": "element",
          "name": "dc:format",
          "children": [
            {
              "type": "text",
              "text": "text/xml"
            }
          ]
        },
        {
          "type": "element",
          "name": "dc:identifier",
          "children": [
            {
              "type": "text",
              "text": "N20398"
            }
          ]
        },
        {
          "type": "element",
          "name": "dc:source",
          "children": [
            {
              "type": "text",
              "text": "https://www.legifrance.gouv.fr/codes/id/LEGISCTA000030722211, https://www.education.gouv.fr/bo/2025/Hebdo15/MENS2508577C"
            }
          ]
        },
        {
          "type": "element",
          "name": "dc:language",
          "children": [
            {
              "type": "text",
              "text": "Fr"
            }
          ]
        },
        {
          "type": "element",
          "name": "dc:relation",
          "children": [
            {
              "type": "text",
              "text": "isPartOf N19805"
            }
          ]
        },
        {
          "type": "element",
          "name": "dc:coverage",
          "children": [
            {
              "type": "text",
              "text": "France entière"
            }
          ]
        },
        {
          "type": "element",
          "name": "dc:rights",
          "children": [
            {
              "type": "text",
              "text": "https://www.service-public.gouv.fr/a-propos/mentions-legales"
            }
          ]
        },
        {
          "type": "element",
          "name": "SurTitre",
          "children": [
            {
              "type": "text",
              "text": "Dossier"
            }
          ]
        },
        {
          "type": "element",
          "name": "Audience",
          "children": [
            {
              "type": "text",
              "text": "Particuliers"
            }
          ]
        },
        {
          "type": "element",
          "name": "Canal",
          "children": [
            {
              "type": "text",
              "text": "www.service-public.fr"
            }
          ]
        },
        {
          "type": "element",
          "name": "Cible",
          "children": [
            {
              "type": "text",
              "text": "Étudiant, Jeune"
            }
          ]
        },
        {
          "type": "element",
          "name": "FilDAriane",
          "children": [
            {
              "type": "element",
              "name": "Niveau",
              "attributes": {
                "ID": "Particuliers"
              },
              "children": [
                {
                  "type": "text",
                  "text": "Accueil particuliers"
                }
              ]
            },
            {
              "type": "element",
              "name": "Niveau",
              "attributes": {
                "ID": "N19805"
              },
              "children": [
                {
                  "type": "text",
                  "text": "Famille - Scolarité"
                }
              ]
            },
            {
              "type": "element",
              "name": "Niveau",
              "attributes": {
                "ID": "N20398",
                "type": "Dossier"
              },
              "children": [
                {
                  "type": "text",
                  "text": "Bourses et aides pour étudiant"
                }
              ]
            }
          ]
        },
        {
          "type": "element",
          "name": "Theme",
          "attributes": {
            "ID": "N19805"
          },
          "children": [
            {
              "type": "element",
              "name": "Titre",
              "children": [
                {
                  "type": "text",
                  "text": "Famille - Scolarité"
                }
              ]
            }
          ]
        },
        {
          "type": "element",
          "name": "SousThemePere",
          "attributes": {
            "ID": "N20400"
          },
          "children": [
            {
              "type": "text",
              "text": "Études supérieures"
            }
          ]
        },
        {
          "type": "element",
          "name": "SousDossier",
          "attributes": {
            "ID": "N20398-1"
          },
          "children": [
            {
              "type": "element",
              "name": "Titre",
              "children": [
                {
                  "type": "text",
                  "text": "Aides sur critères sociaux et au mérite"
                }
              ]
            },
            {
              "type": "element",
              "name": "Fiche",
              "attributes": {
                "ID": "F12214"
              },
              "children": [
                {
                  "type": "text",
                  "text": "Bourse sur critères sociaux"
                }
              ]
            },
            {
              "type": "element",
              "name": "Fiche",
              "attributes": {
                "ID": "F1010"
              },
              "children": [
                {
                  "type": "text",
                  "text": "Aide au mérite"
                }
              ]
            }
          ]
        },
        {
          "type": "element",
          "name": "SousDossier",
          "attributes": {
            "ID": "N20398-2"
          },
          "children": [
            {
              "type": "element",
              "name": "Titre",
              "children": [
                {
                  "type": "text",
                  "text": "Étudiant rencontrant des difficultés financières"
                }
              ]
            },
            {
              "type": "element",
              "name": "Fiche",
              "attributes": {
                "ID": "F1024"
              },
              "children": [
                {
                  "type": "text",
                  "text": "Allocation annuelle"
                }
              ]
            },
            {
              "type": "element",
              "name": "Fiche",
              "attributes": {
                "ID": "F34073"
              },
              "children": [
                {
                  "type": "text",
                  "text": "Aide ponctuelle"
                }
              ]
            }
          ]
        },
        {
          "type": "element",
          "name": "SousDossier",
          "attributes": {
            "ID": "N20398-3"
          },
          "children": [
            {
              "type": "element",
              "name": "Titre",
              "children": [
                {
                  "type": "text",
                  "text": "Aides à la mobilité"
                }
              ]
            },
            {
              "type": "element",
              "name": "Fiche",
              "attributes": {
                "ID": "F34343"
              },
              "children": [
                {
                  "type": "text",
                  "text": "Étudiant en master"
                }
              ]
            },
            {
              "type": "element",
              "name": "Fiche",
              "attributes": {
                "ID": "F34643"
              },
              "children": [
                {
                  "type": "text",
                  "text": "Bachelier acceptant une mobilité géographique"
                }
              ]
            }
          ]
        },
        {
          "type": "element",
          "name": "Introduction",
          "children": [
            {
              "type": "element",
              "name": "Texte",
              "children": [
                {
                  "type": "element",
                  "name": "Paragraphe",
                  "children": [
                    {
                      "type": "text",
                      "text": "Si vous êtes étudiant ou que vous entrez en première année d'études supérieures, vous pouvez prétendre à des bourses et à des aides en fonction de votre situation. Si vous rencontrez des difficultés financières pour entreprendre et poursuivre vos études, vous pouvez également bénéficier d'aides spécifiques. Des aides à la mobilité, à l'insertion professionnelle et à l’accès à la fonction publique peuvent également vous être attribuées."
                    }
                  ]
                }
              ]
            }
          ]
        },
        {
          "type": "element",
          "name": "VoirAussi",
          "attributes": {
            "important": "non"
          },
          "children": [
            {
              "type": "element",
              "name": "Dossier",
              "attributes": {
                "ID": "N20360",
                "audience": "Particuliers"
              },
              "children": [
                {
                  "type": "element",
                  "name": "Titre",
                  "children": [
                    {
                      "type": "text",
                      "text": "Aides personnelles au logement"
                    }
                  ]
                },
                {
                  "type": "element",
                  "name": "Theme",
                  "attributes": {
                    "ID": "N19808"
                  },
                  "children": [
                    {
                      "type": "element",
                      "name": "Titre",
                      "children": [
                        {
                          "type": "text",
                          "text": "Logement"
                        }
                      ]
                    }
                  ]
                }
              ]
            },
            {
              "type": "element",
              "name": "Dossier",
              "attributes": {
                "ID": "N13511",
                "audience": "Particuliers"
              },
              "children": [
                {
                  "type": "element",
                  "name": "Titre",
                  "children": [
                    {
                      "type": "text",
                      "text": "Étudier à l'étranger"
                    }
                  ]
                },
                {
                  "type": "element",
                  "name": "Theme",
                  "attributes": {
                    "ID": "N19805"
                  },
                  "children": [
                    {
                      "type": "element",
                      "name": "Titre",
                      "children": [
                        {
                          "type": "text",
                          "text": "Famille - Scolarité"
                        }
                      ]
                    }
                  ]
                }
              ]
            }
          ]
        },
        {
          "type": "element",
          "name": "Reference",
          "attributes": {
            "type": "Texte de référence",
            "URL": "https://www.legifrance.gouv.fr/codes/id/LEGISCTA000030722211",
            "ID": "R19457"
          },
          "children": [
            {
              "type": "element",
              "name": "Titre",
              "children": [
                {
                  "type": "text",
                  "text": "Code de l'éducation : articles D821-1 à R821-5"
                }
              ]
            },
            {
              "type": "element",
              "name": "Complement",
              "children": [
                {
                  "type": "text",
                  "text": "Bourses d'enseignement supérieur"
                }
              ]
            }
          ]
        },
        {
          "type": "element",
          "name": "Reference",
          "attributes": {
            "type": "Texte de référence",
            "URL": "https://www.education.gouv.fr/bo/2025/Hebdo15/MENS2508577C",
            "ID": "R19264"
          },
          "children": [
            {
              "type": "element",
              "name": "Titre",
              "children": [
                {
                  "type": "text",
                  "text": "Circulaire du 28 mars 2025 relative aux bourses d'enseignement supérieur sur critères sociaux, des aides au mérite et des aides à la mobilité internationale pour 2025-2026"
                }
              ]
            }
          ]
        },
        {
          "type": "element",
          "name": "ServiceEnLigne",
          "attributes": {
            "ID": "R18296",
            "URL": "http://www.etudiant.gouv.fr/cid97527/simulateur-de-bourse.html",
            "audience": "Particuliers",
            "type": "Simulateur"
          },
          "children": [
            {
              "type": "element",
              "name": "Titre",
              "children": [
                {
                  "type": "text",
                  "text": "Étudiant : calculer votre droit à bourse sur critères sociaux"
                }
              ]
            },
            {
              "type": "element",
              "name": "Source",
              "attributes": {
                "ID": "R30627"
              },
              "children": [
                {
                  "type": "text",
                  "text": "Centre national des œuvres universitaires et scolaires (Cnous)"
                }
              ]
            }
          ]
        },
        {
          "type": "element",
          "name": "ServiceEnLigne",
          "attributes": {
            "ID": "R16390",
            "URL": "https://www.messervices.etudiant.gouv.fr",
            "audience": "Particuliers",
            "type": "Téléservice"
          },
          "children": [
            {
              "type": "element",
              "name": "Titre",
              "children": [
                {
                  "type": "text",
                  "text": "Mes services étudiant"
                }
              ]
            },
            {
              "type": "element",
              "name": "Source",
              "attributes": {
                "ID": "R30775"
              },
              "children": [
                {
                  "type": "text",
                  "text": "Ministère chargé de l'enseignement supérieur et de la recherche"
                }
              ]
            }
          ]
        },
        {
          "type": "element",
          "name": "ServiceEnLigne",
          "attributes": {
            "ID": "R36750",
            "URL": "https://www.formulaires.service-public.gouv.fr/gf/cerfa_15065.do",
            "audience": "Particuliers",
            "format": "application/pdf",
            "poids": "71.7 KB",
            "numerocerfa": "15065*04",
            "type": "Formulaire"
          },
          "children": [
            {
              "type": "element",
              "name": "Titre",
              "children": [
                {
                  "type": "text",
                  "text": "Demande de bourse d'études à l'École nationale supérieure maritime"
                }
              ]
            },
            {
              "type": "element",
              "name": "Source",
              "attributes": {
                "ID": "R43570"
              },
              "children": [
                {
                  "type": "text",
                  "text": "Ministère chargé de la mer et de la pêche"
                }
              ]
            }
          ]
        },
        {
          "type": "element",
          "name": "ServiceEnLigne",
          "attributes": {
            "ID": "R21220",
            "URL": "https://www.formulaires.service-public.gouv.fr/gf/cerfa_11779.do",
            "audience": "Particuliers",
            "format": "application/pdf",
            "poids": "168.9 KB",
            "numerocerfa": "11779*11",
            "type": "Formulaire"
          },
          "children": [
            {
              "type": "element",
              "name": "Titre",
              "children": [
                {
                  "type": "text",
                  "text": "Demande de bourse nationale d'études du second degré (enseignement agricole)"
                }
              ]
            },
            {
              "type": "element",
              "name": "Source",
              "attributes": {
                "ID": "R54776"
              },
              "children": [
                {
                  "type": "text",
                  "text": "Ministère chargé de l'agriculture"
                }
              ]
            }
          ]
        },
        {
          "type": "element",
          "name": "ServiceEnLigne",
          "attributes": {
            "ID": "R66163",
            "URL": "https://www.1jeune1solution.gouv.fr/mes-aides",
            "audience": "Particuliers",
            "type": "Simulateur"
          },
          "children": [
            {
              "type": "element",
              "name": "Titre",
              "children": [
                {
                  "type": "text",
                  "text": "1jeune1solution : découvrez toutes les aides auxquelles vous avez droit"
                }
              ]
            },
            {
              "type": "element",
              "name": "Source",
              "attributes": {
                "ID": "R30661"
              },
              "children": [
                {
                  "type": "text",
                  "text": "Ministère chargé du travail"
                }
              ]
            }
          ]
        },
        {
          "type": "element",
          "name": "PourEnSavoirPlus",
          "attributes": {
            "type": "Information pratique",
            "ID": "R3017",
            "URL": "https://ladom.fr/vie-etudiante/pme/",
            "audience": "Particuliers"
          },
          "children": [
            {
              "type": "element",
              "name": "Titre",
              "children": [
                {
                  "type": "text",
                  "text": "Le passeport mobilité pour les étudiants d'outre-mer"
                }
              ]
            },
            {
              "type": "element",
              "name": "Source",
              "attributes": {
                "ID": "R30603"
              },
              "children": [
                {
                  "type": "text",
                  "text": "Ministère chargé de l'intérieur"
                }
              ]
            }
          ]
        },
        {
          "type": "element",
          "name": "PourEnSavoirPlus",
          "attributes": {
            "type": "Information pratique",
            "ID": "R3015",
            "URL": "http://www.etudiant.gouv.fr/pid33628/vos-aides-financieres.html",
            "audience": "Particuliers"
          },
          "children": [
            {
              "type": "element",
              "name": "Titre",
              "children": [
                {
                  "type": "text",
                  "text": "Bourses et aides financières dans l'enseignement supérieur"
                }
              ]
            },
            {
              "type": "element",
              "name": "Source",
              "attributes": {
                "ID": "R30627"
              },
              "children": [
                {
                  "type": "text",
                  "text": "Centre national des œuvres universitaires et scolaires (Cnous)"
                }
              ]
            }
          ]
        },
        {
          "type": "element",
          "name": "PourEnSavoirPlus",
          "attributes": {
            "type": "Information pratique",
            "ID": "R2897",
            "URL": "http://www.etudiant.gouv.fr/pid33632/vous-loger.html",
            "audience": "Particuliers"
          },
          "children": [
            {
              "type": "element",
              "name": "Titre",
              "children": [
                {
                  "type": "text",
                  "text": "Logement étudiant"
                }
              ]
            },
            {
              "type": "element",
              "name": "Source",
              "attributes": {
                "ID": "R30627"
              },
              "children": [
                {
                  "type": "text",
                  "text": "Centre national des œuvres universitaires et scolaires (Cnous)"
                }
              ]
            }
          ]
        },
        {
          "type": "element",
          "name": "PourEnSavoirPlus",
          "attributes": {
            "type": "Information pratique",
            "ID": "R2898",
            "URL": "https://www.etudiant.gouv.fr/fr/carte-pour-trouver-les-resto-u-235",
            "audience": "Particuliers"
          },
          "children": [
            {
              "type": "element",
              "name": "Titre",
              "children": [
                {
                  "type": "text",
                  "text": "Restaurant universitaire"
                }
              ]
            },
            {
              "type": "element",
              "name": "Source",
              "attributes": {
                "ID": "R30627"
              },
              "children": [
                {
                  "type": "text",
                  "text": "Centre national des œuvres universitaires et scolaires (Cnous)"
                }
              ]
            }
          ]
        },
        {
          "type": "element",
          "name": "QuestionReponse",
          "attributes": {
            "ID": "F32456",
            "audience": "Particuliers"
          },
          "children": [
            {
              "type": "element",
              "name": "Titre",
              "children": [
                {
                  "type": "text",
                  "text": "Quelles aides peut percevoir un étudiant ?"
                }
              ]
            }
          ]
        },
        {
          "type": "element",
          "name": "QuestionReponse",
          "attributes": {
            "ID": "F17482",
            "audience": "Particuliers"
          },
          "children": [
            {
              "type": "element",
              "name": "Titre",
              "children": [
                {
                  "type": "text",
                  "text": "Que sont les bourses Talents ?"
                }
              ]
            }
          ]
        },
        {
          "type": "element",
          "name": "QuestionReponse",
          "attributes": {
            "ID": "F12216",
            "audience": "Particuliers"
          },
          "children": [
            {
              "type": "element",
              "name": "Titre",
              "children": [
                {
                  "type": "text",
                  "text": "DSE (dossier social étudiant) : comment demander une bourse et/ou un logement ?"
                }
              ]
            }
          ]
        },
        {
          "type": "element",
          "name": "QuestionReponse",
          "attributes": {
            "ID": "F12215",
            "audience": "Particuliers"
          },
          "children": [
            {
              "type": "element",
              "name": "Titre",
              "children": [
                {
                  "type": "text",
                  "text": "Un étudiant peut-il percevoir la bourse pendant les vacances d'été ?"
                }
              ]
            }
          ]
        },
        {
          "type": "element",
          "name": "QuestionReponse",
          "attributes": {
            "ID": "F18291",
            "audience": "Particuliers"
          },
          "children": [
            {
              "type": "element",
              "name": "Titre",
              "children": [
                {
                  "type": "text",
                  "text": "Un étudiant peut-il cumuler la bourse sur critères sociaux avec un emploi ou une autre aide ?"
                }
              ]
            }
          ]
        },
        {
          "type": "element",
          "name": "QuestionReponse",
          "attributes": {
            "ID": "F31912",
            "audience": "Particuliers"
          },
          "children": [
            {
              "type": "element",
              "name": "Titre",
              "children": [
                {
                  "type": "text",
                  "text": "Comment demander un logement étudiant au Crous ?"
                }
              ]
            }
          ]
        }
      ]
    }
  ]
}