{
  "id": "F1124",
  "children": [
    {
      "type": "element",
      "name": "Publication",
      "attributes": {
        "xmlns:dc": "http://purl.org/dc/elements/1.1/",
        "xmlns:xsi": "http://www.w3.org/2001/XMLSchema-instance",
        "ID": "F1124",
        "type": "Fiche d'information conditionnée",
        "xsi:noNamespaceSchemaLocation": "../Schemas/3.3/Publication.xsd",
        "spUrl": "https://www.service-public.fr/associations/vosdroits/F1124"
      },
      "children": [
        {
          "type": "element",
          "name": "dc:title",
          "children": [
            {
              "type": "text",
              "text": "Assurance des associations"
            }
          ]
        },
        {
          "type": "element",
          "name": "dc:creator",
          "children": [
            {
              "type": "text",
              "text": "Direction de l'information légale et administrative"
            }
          ]
        },
        {
          "type": "element",
          "name": "dc:subject",
          "children": [
            {
              "type": "text",
              "text": "Fonctionnement d'une association"
            }
          ]
        },
        {
          "type": "element",
          "name": "dc:description",
          "children": [
            {
              "type": "text",
              "text": "Une association est exposée à divers risques du fait de l'exercice même de son activité, du fait de ses biens mobiliers ou immobiliers."
            }
          ]
        },
        {
          "type": "element",
          "name": "dc:publisher",
          "children": [
            {
              "type": "text",
              "text": "Direction de l'information légale et administrative"
            }
          ]
        },
        {
          "type": "element",
          "name": "dc:contributor",
          "children": [
            {
              "type": "text",
              "text": "Direction de l'information légale et administrative (Premier ministre)"
            }
          ]
        },
        {
          "type": "element",
          "name": "dc:date",
          "children": [
            {
              "type": "text",
              "text": "modified 2021-06-29"
            }
          ]
        },
        {
          "type": "element",
          "name": "dc:type",
          "children": [
            {
              "type": "text",
              "text": "Fiche pratique"
            }
          ]
        },
        {
          "type": "element",
          "name": "dc:format",
          "children": [
            {
              "type": "text",
              "text": "text/xml"
            }
          ]
        },
        {
          "type": "element",
          "name": "dc:identifier",
          "children": [
            {
              "type": "text",
              "text": "F1124"
            }
          ]
        },
        {
          "type": "element",
          "name": "dc:source",
          "children": [
            {
              "type": "text",
              "text": "https://www.legifrance.gouv.fr/codes/id/LEGISCTA000032021488/"
            }
          ]
        },
        {
          "type": "element",
          "name": "dc:language",
          "children": [
            {
              "type": "text",
              "text": "Fr"
            }
          ]
        },
        {
          "type": "element",
          "name": "dc:relation",
          "children": [
            {
              "type": "text",
              "text": "isPartOf N31331"
            }
          ]
        },
        {
          "type": "element",
          "name": "dc:coverage",
          "children": [
            {
              "type": "text",
              "text": "France entière"
            }
          ]
        },
        {
          "type": "element",
          "name": "dc:rights",
          "children": [
            {
              "type": "text",
              "text": "https://www.service-public.fr/a-propos/mentions-legales"
            }
          ]
        },
        {
          "type": "element",
          "name": "SurTitre",
          "children": [
            {
              "type": "text",
              "text": "Fiche pratique"
            }
          ]
        },
        {
          "type": "element",
          "name": "Audience",
          "children": [
            {
              "type": "text",
              "text": "Associations"
            }
          ]
        },
        {
          "type": "element",
          "name": "Canal",
          "children": [
            {
              "type": "text",
              "text": "www.service-public.fr"
            }
          ]
        },
        {
          "type": "element",
          "name": "FilDAriane",
          "children": [
            {
              "type": "element",
              "name": "Niveau",
              "attributes": {
                "ID": "Associations"
              },
              "children": [
                {
                  "type": "text",
                  "text": "Accueil associations"
                }
              ]
            },
            {
              "type": "element",
              "name": "Niveau",
              "attributes": {
                "ID": "N31404"
              },
              "children": [
                {
                  "type": "text",
                  "text": "Fonctionnement d'une association"
                }
              ]
            },
            {
              "type": "element",
              "name": "Niveau",
              "attributes": {
                "ID": "N31331"
              },
              "children": [
                {
                  "type": "text",
                  "text": "Assurance et responsabilité d'une association"
                }
              ]
            },
            {
              "type": "element",
              "name": "Niveau",
              "attributes": {
                "ID": "F1124",
                "type": "Fiche d'information conditionnée"
              },
              "children": [
                {
                  "type": "text",
                  "text": "Assurance des associations"
                }
              ]
            }
          ]
        },
        {
          "type": "element",
          "name": "Theme",
          "attributes": {
            "ID": "N31404"
          },
          "children": [
            {
              "type": "element",
              "name": "Titre",
              "children": [
                {
                  "type": "text",
                  "text": "Fonctionnement d'une association"
                }
              ]
            }
          ]
        },
        {
          "type": "element",
          "name": "DossierPere",
          "attributes": {
            "ID": "N31331"
          },
          "children": [
            {
              "type": "element",
              "name": "Titre",
              "children": [
                {
                  "type": "text",
                  "text": "Assurance et responsabilité d'une association"
                }
              ]
            },
            {
              "type": "element",
              "name": "Fiche",
              "attributes": {
                "ID": "F1124"
              },
              "children": [
                {
                  "type": "text",
                  "text": "Assurance"
                }
              ]
            },
            {
              "type": "element",
              "name": "Fiche",
              "attributes": {
                "ID": "F1127"
              },
              "children": [
                {
                  "type": "text",
                  "text": "Constitution de partie civile"
                }
              ]
            }
          ]
        },
        {
          "type": "element",
          "name": "Introduction",
          "children": [
            {
              "type": "element",
              "name": "Texte",
              "children": [
                {
                  "type": "element",
                  "name": "Paragraphe",
                  "children": [
                    {
                      "type": "text",
                      "text": "Une association doit souscrire une assurance responsabilité civile pour couvrir les dommages causés à un tiers (personne extérieure à l'association) par ses salariés, bénévoles, adhérents et dirigeants. Si l'association est locataire d'un logement et/ou propriétaire de véhicules, la loi lui impose également de souscrire des contrats contre les risques locatifs et les accidents automobiles. L'association peut proposer une assurance à ses adhérents."
                    }
                  ]
                }
              ]
            }
          ]
        },
        {
          "type": "element",
          "name": "Texte",
          "children": [
            {
              "type": "element",
              "name": "Chapitre",
              "children": [
                {
                  "type": "element",
                  "name": "Titre",
                  "children": [
                    {
                      "type": "element",
                      "name": "Paragraphe",
                      "children": [
                        {
                          "type": "text",
                          "text": "Risques couverts par l'assurance responsabilité civile"
                        }
                      ]
                    }
                  ]
                },
                {
                  "type": "element",
                  "name": "Paragraphe",
                  "children": [
                    {
                      "type": "text",
                      "text": "L'assurance responsabilité civile sert à indemniser les dommage causés ou subis par les salariés, bénévoles, adhérents et dirigeants de l'association."
                    }
                  ]
                },
                {
                  "type": "element",
                  "name": "Paragraphe",
                  "children": [
                    {
                      "type": "text",
                      "text": "Elle peut également garantir les préjudices (dommages) causés à des participants, spectateurs ou usagers de l'association."
                    }
                  ]
                },
                {
                  "type": "element",
                  "name": "Paragraphe",
                  "children": [
                    {
                      "type": "text",
                      "text": "La loi impose de souscrire cette assurance aux associations suivantes :"
                    }
                  ]
                },
                {
                  "type": "element",
                  "name": "Liste",
                  "attributes": {
                    "type": "puce"
                  },
                  "children": [
                    {
                      "type": "element",
                      "name": "Item",
                      "children": [
                        {
                          "type": "element",
                          "name": "Paragraphe",
                          "children": [
                            {
                              "type": "text",
                              "text": "Associations et fédérations sportives, les associations organisatrices de manifestations sportives, les associations exploitant des établissements d'activités physiques et sportives"
                            }
                          ]
                        }
                      ]
                    },
                    {
                      "type": "element",
                      "name": "Item",
                      "children": [
                        {
                          "type": "element",
                          "name": "Paragraphe",
                          "children": [
                            {
                              "type": "text",
                              "text": "Associations communales de chasse agréées"
                            }
                          ]
                        }
                      ]
                    },
                    {
                      "type": "element",
                      "name": "Item",
                      "children": [
                        {
                          "type": "element",
                          "name": "Paragraphe",
                          "children": [
                            {
                              "type": "text",
                              "text": "Associations ayant pour objet l'organisation ou la vente de voyages ou de séjours individuels ou collectifs"
                            }
                          ]
                        }
                      ]
                    },
                    {
                      "type": "element",
                      "name": "Item",
                      "children": [
                        {
                          "type": "element",
                          "name": "Paragraphe",
                          "children": [
                            {
                              "type": "text",
                              "text": "Associations gestionnaires d'établissements d'accueil d'enfants de moins de 6 ans (crèches, halte-garderies, etc.)"
                            }
                          ]
                        }
                      ]
                    },
                    {
                      "type": "element",
                      "name": "Item",
                      "children": [
                        {
                          "type": "element",
                          "name": "Paragraphe",
                          "children": [
                            {
                              "type": "text",
                              "text": "Associations organisant l'accueil de mineurs ou exploitant des lieux d'hébergement de mineurs"
                            }
                          ]
                        }
                      ]
                    },
                    {
                      "type": "element",
                      "name": "Item",
                      "children": [
                        {
                          "type": "element",
                          "name": "Paragraphe",
                          "children": [
                            {
                              "type": "text",
                              "text": "Associations gestionnaires d'établissements d'accueil d'enfants ou d'adolescents présentant des déficiences intellectuelles"
                            }
                          ]
                        }
                      ]
                    },
                    {
                      "type": "element",
                      "name": "Item",
                      "children": [
                        {
                          "type": "element",
                          "name": "Paragraphe",
                          "children": [
                            {
                              "type": "text",
                              "text": "Associations exerçant une activité de prévention, de diagnostic ou de soins"
                            }
                          ]
                        }
                      ]
                    }
                  ]
                },
                {
                  "type": "element",
                  "name": "Paragraphe",
                  "children": [
                    {
                      "type": "text",
                      "text": "Si un membre de l'association blesse un autre membre, la garantie responsabilité civile intervient si le contrat prévoit qu'ils sont considérés comme n'ayant pas de lien entre eux (tiers)."
                    }
                  ]
                }
              ]
            },
            {
              "type": "element",
              "name": "Chapitre",
              "children": [
                {
                  "type": "element",
                  "name": "Titre",
                  "children": [
                    {
                      "type": "element",
                      "name": "Paragraphe",
                      "children": [
                        {
                          "type": "text",
                          "text": "Assurance des véhicules"
                        }
                      ]
                    }
                  ]
                },
                {
                  "type": "element",
                  "name": "Paragraphe",
                  "children": [
                    {
                      "type": "text",
                      "text": "Une association propriétaire de véhicules doit souscrire une assurance responsabilité civile "
                    },
                    {
                      "type": "element",
                      "name": "LienInterne",
                      "attributes": {
                        "LienPublication": "F2628",
                        "type": "Fiche d'information conditionnée",
                        "audience": "Particuliers"
                      },
                      "children": [
                        {
                          "type": "text",
                          "text": "(assurance obligatoire au tiers)"
                        }
                      ]
                    },
                    {
                      "type": "text",
                      "text": " pour couvrir les dommages lors de la circulation du véhicule. Elle peut choisir une "
                    },
                    {
                      "type": "element",
                      "name": "LienInterne",
                      "attributes": {
                        "LienPublication": "N32",
                        "type": "Dossier",
                        "audience": "Particuliers"
                      },
                      "children": [
                        {
                          "type": "text",
                          "text": "garantie plus étendue"
                        }
                      ]
                    },
                    {
                      "type": "text",
                      "text": "."
                    }
                  ]
                },
                {
                  "type": "element",
                  "name": "Attention",
                  "children": [
                    {
                      "type": "element",
                      "name": "Titre",
                      "children": [
                        {
                          "type": "text",
                          "text": "Attention"
                        }
                      ]
                    },
                    {
                      "type": "element",
                      "name": "Paragraphe",
                      "children": [
                        {
                          "type": "text",
                          "text": "lorsqu'un bénévole utilise sa voiture personnelle, dans le cadre de son activité associative, c'est à lui d'assurer son véhicule."
                        }
                      ]
                    }
                  ]
                }
              ]
            },
            {
              "type": "element",
              "name": "Chapitre",
              "children": [
                {
                  "type": "element",
                  "name": "Titre",
                  "children": [
                    {
                      "type": "element",
                      "name": "Paragraphe",
                      "children": [
                        {
                          "type": "text",
                          "text": "Assurance des locaux"
                        }
                      ]
                    }
                  ]
                },
                {
                  "type": "element",
                  "name": "Paragraphe",
                  "children": [
                    {
                      "type": "text",
                      "text": "Une association locataire doit souscrire une "
                    },
                    {
                      "type": "element",
                      "name": "LienInterne",
                      "attributes": {
                        "LienPublication": "F1349",
                        "type": "Fiche d'information conditionnée",
                        "audience": "Particuliers"
                      },
                      "children": [
                        {
                          "type": "text",
                          "text": "garantie des risques locatifs"
                        }
                      ]
                    },
                    {
                      "type": "text",
                      "text": " pour couvrir les dommages causés à l'immeuble en cas d'incendie, de dégât des eaux ou d'explosion."
                    }
                  ]
                },
                {
                  "type": "element",
                  "name": "Paragraphe",
                  "children": [
                    {
                      "type": "text",
                      "text": "La souscription n'est pas obligatoire si "
                    },
                    {
                      "type": "element",
                      "name": "LienInterne",
                      "attributes": {
                        "LienPublication": "F2023",
                        "type": "Fiche d'information conditionnée",
                        "audience": "Particuliers"
                      },
                      "children": [
                        {
                          "type": "text",
                          "text": "l'association est propriétaire"
                        }
                      ]
                    },
                    {
                      "type": "text",
                      "text": " de son local. La souscription est, toutefois, vivement conseillée."
                    }
                  ]
                },
                {
                  "type": "element",
                  "name": "Paragraphe",
                  "children": [
                    {
                      "type": "text",
                      "text": "L'association peut choisir une "
                    },
                    {
                      "type": "element",
                      "name": "LienInterne",
                      "attributes": {
                        "LienPublication": "N44",
                        "type": "Dossier",
                        "audience": "Particuliers"
                      },
                      "children": [
                        {
                          "type": "text",
                          "text": "garantie plus étendue"
                        }
                      ]
                    },
                    {
                      "type": "text",
                      "text": " pour couvrir notamment les dommages causés aux voisins ou à des tiers, et les dommages causés à ses biens."
                    }
                  ]
                },
                {
                  "type": "element",
                  "name": "Attention",
                  "children": [
                    {
                      "type": "element",
                      "name": "Titre",
                      "children": [
                        {
                          "type": "text",
                          "text": "Attention"
                        }
                      ]
                    },
                    {
                      "type": "element",
                      "name": "Paragraphe",
                      "children": [
                        {
                          "type": "text",
                          "text": "lorsque le local de l'association est le logement d'un membre, celui-ci doit "
                        },
                        {
                          "type": "element",
                          "name": "LienInterne",
                          "attributes": {
                            "LienPublication": "F2594",
                            "type": "Fiche d'information conditionnée",
                            "audience": "Particuliers"
                          },
                          "children": [
                            {
                              "type": "text",
                              "text": "avertir son assureur"
                            }
                          ]
                        },
                        {
                          "type": "text",
                          "text": " de cette situation."
                        }
                      ]
                    }
                  ]
                }
              ]
            }
          ]
        },
        {
          "type": "element",
          "name": "OuSAdresser",
          "attributes": {
            "ID": "R17216",
            "sve": "non",
            "type": "Local"
          },
          "children": [
            {
              "type": "element",
              "name": "Titre",
              "children": [
                {
                  "type": "text",
                  "text": "Point ressource à la vie associative"
                }
              ]
            },
            {
              "type": "element",
              "name": "RessourceWeb",
              "attributes": {
                "URL": "http://www.associations.gouv.fr/les-centres-de-ressources-pour-les-responsables-ou-createurs-d-association.html"
              }
            },
            {
              "type": "element",
              "name": "Source",
              "attributes": {
                "ID": "R30678"
              },
              "children": [
                {
                  "type": "text",
                  "text": "Ministère chargé de la vie associative"
                }
              ]
            }
          ]
        },
        {
          "type": "element",
          "name": "Reference",
          "attributes": {
            "type": "Texte de référence",
            "URL": "https://www.legifrance.gouv.fr/codes/id/LEGISCTA000032021488/",
            "ID": "R610"
          },
          "children": [
            {
              "type": "element",
              "name": "Titre",
              "children": [
                {
                  "type": "text",
                  "text": "Code civil : articles 1240 à 1244"
                }
              ]
            }
          ]
        },
        {
          "type": "element",
          "name": "ServiceEnLigne",
          "attributes": {
            "ID": "R14591",
            "URL": "http://www.ameli.fr/fileadmin/user_upload/formulaires/S6104bis.pdf",
            "format": "application/pdf",
            "poids": "46.7 KB",
            "numerocerfa": "60-3997",
            "autrenumero": "S6104 bis",
            "type": "Formulaire"
          },
          "children": [
            {
              "type": "element",
              "name": "Titre",
              "children": [
                {
                  "type": "text",
                  "text": "Déclaration à la Sécurité sociale des bénévoles des organismes d'intérêt général (hors organismes sociaux)"
                }
              ]
            },
            {
              "type": "element",
              "name": "Source",
              "attributes": {
                "ID": "R30675"
              },
              "children": [
                {
                  "type": "text",
                  "text": "Caisse nationale d'assurance maladie (Cnam)"
                }
              ]
            }
          ]
        },
        {
          "type": "element",
          "name": "PourEnSavoirPlus",
          "attributes": {
            "type": "Information pratique",
            "ID": "R48336",
            "URL": "http://www.associations.gouv.fr/le-benevole-victime-d-un-dommage.html",
            "audience": "Associations"
          },
          "children": [
            {
              "type": "element",
              "name": "Titre",
              "children": [
                {
                  "type": "text",
                  "text": "Bénévole victime d'un dommage"
                }
              ]
            },
            {
              "type": "element",
              "name": "Source",
              "attributes": {
                "ID": "R30678"
              },
              "children": [
                {
                  "type": "text",
                  "text": "Ministère chargé de la vie associative"
                }
              ]
            }
          ]
        },
        {
          "type": "element",
          "name": "PourEnSavoirPlus",
          "attributes": {
            "type": "Information pratique",
            "ID": "R33428",
            "URL": "http://www.associations.gouv.fr/la-protection-sociale-du-benevole.html",
            "audience": "Associations"
          },
          "children": [
            {
              "type": "element",
              "name": "Titre",
              "children": [
                {
                  "type": "text",
                  "text": "Protection sociale du bénévole"
                }
              ]
            },
            {
              "type": "element",
              "name": "Source",
              "attributes": {
                "ID": "R30678"
              },
              "children": [
                {
                  "type": "text",
                  "text": "Ministère chargé de la vie associative"
                }
              ]
            }
          ]
        },
        {
          "type": "element",
          "name": "QuestionReponse",
          "attributes": {
            "ID": "F31403",
            "audience": "Particuliers"
          },
          "children": [
            {
              "type": "text",
              "text": "Quelle assurance faut-il pour pratiquer le covoiturage ?"
            }
          ]
        },
        {
          "type": "element",
          "name": "CommentFaireSi",
          "attributes": {
            "ID": "F31613",
            "audience": "Associations"
          },
          "children": [
            {
              "type": "text",
              "text": "L'association organise un événement : fête, manifestation, vide-grenier"
            }
          ]
        }
      ]
    }
  ]
}